Workbook

Sheet Summary
A1: TECHM8 Products (28) - Pre-Import Review
A2: Review only. Nothing in this workbook has been imported into Supabase or the POS.
A4: Review metric | B4: Count | D4: Classification rule | E4: How it is applied
A5: Source products | B5: =COUNTA('Product Review'!B2:B35) -> 34 | D5: Classify by product essence | E5: Use what the item is, not where it was previously stored in RepairDesk.
A6: Recommended for import | B6: =COUNTIF('Product Review'!C2:C35,"Import") -> 23 | D6: Use existing POS hierarchy | E6: Do not create new categories for this batch. Use existing second-level categories.
A7: Clarification required | B7: =COUNTIF('Product Review'!C2:C35,"Clarify") -> 5 | D7: Group styles, preserve sellable variants | E7: One card per style; colours remain independent SKU/stock rows.
A8: Recommended exclusion | B8: =COUNTIF('Product Review'!C2:C35,"Exclude") -> 6 | D8: Exclude non-merchandise | E8: Packaging, shop credit and generic Special/Misc placeholders do not belong in product inventory.
A9: Missing cost | B9: =COUNTIF('Product Review'!R2:R35,"Missing cost") -> 17 | D9: Block incomplete items | E9: Unknown product identity, missing cost or suspicious cost=retail must be confirmed before import.
A10: Cost and retail both require verification | B10: =COUNTIF('Product Review'!R2:R35,"Verify cost and retail") -> 2
A13: Immediate owner action | B13: Affected products | C13: Required input
A14: Enter missing costs | B14: 13 clear import products plus 4 unclear products | C14: Fill Owner Cost in Product Review.
A15: Verify suspicious prices | B15: RGB Digital Clock; Music-Reactive RGB Light | C15: Confirm both cost and retail because each currently has zero margin.
A16: Resolve ambiguous products | B16: CTF MagSafe stand; Card Strap Holder; Drone Map; Phone Tag; $2 SIM | C16: Confirm image/function and exact name/category.
A17: Resolve duplicate SKU | B17: CTF Earbuds Pouch and CTF MagSafe stand both use 1032168 | C17: Create separate internal SKUs before import.
A18: Exclude non-products | B18: TechM8 bags; Special Order; Shop Credit; Special; Miscellaneous & Other Products | C18: Keep outside the sellable product catalogue.

Sheet Product Review
A1: Source Row | B1: Item ID | C1: Recommendation | D1: Original Category | E1: Original Name | F1: Proposed Name | G1: POS Main Category | H1: POS Subcategory | I1: Product Group | J1: Original SKU | K1: SKU Action | L1: Original Cost | M1: Owner Cost | N1: Final Cost | O1: Original Retail | P1: Owner Retail | Q1: Final Retail | R1: Price Status | S1: Required Modification | T1: Classification Reason | U1: Image Check | V1: Review Status | W1: Owner Approval | X1: Owner Notes
A2: 3 | B2: 10888 | C2: Import | D2: Card Holder & Pop Scoket > Magsafe Card Holder | E2: Magsafe Card Holder Stand-Wallet Black | F2: MagSafe Stand Wallet - Black | G2: Mounts & Holders | H2: Wallets, Card Holders & Grips | I2: MagSafe Stand Wallet | J2: 108881499 | K2: Keep source SKU | L2: 3 | N2: =IF(M2<>"",M2,L2) -> 3 | O2: 35 | Q2: =IF(P2<>"",P2,O2) -> 35 | R2: Ready | S2: Standardize MagSafe spelling and product name; group by style and colour. | T2: A phone-attached wallet/stand is a wallet and grip accessory. | U2: Not included in export; retrieve/verify in RepairDesk before import | V2: =IF(C2="Exclude","EXCLUDE",IF(OR(C2="Clarify",N2<=0,Q2<=0,R2="Verify cost and retail"),"REVIEW","READY")) -> READY | W2: Pending
A3: 4 | B3: 10857 | C3: Import | D3: Card Holder & Pop Scoket > Magsafe Pop Scoket | E3: Magsafe Silicone Phone Holder Purple | F3: MagSafe Silicone Phone Grip - Purple | G3: Mounts & Holders | H3: Wallets, Card Holders & Grips | I3: MagSafe Silicone Phone Grip | J3: 108571484 | K3: Keep source SKU | L3: 2 | N3: =IF(M3<>"",M3,L3) -> 2 | O3: 29 | Q3: =IF(P3<>"",P3,O3) -> 29 | R3: Ready | S3: Rename from Phone Holder to Phone Grip; group all colours. | T3: A MagSafe pop socket/grip belongs with phone grips, not vehicle mounts. | U3: Not included in export; retrieve/verify in RepairDesk before import | V3: =IF(C3="Exclude","EXCLUDE",IF(OR(C3="Clarify",N3<=0,Q3<=0,R3="Verify cost and retail"),"REVIEW","READY")) -> READY | W3: Pending
A4: 5 | B4: 10856 | C4: Import | D4: Card Holder & Pop Scoket > Magsafe Pop Scoket | E4: Magsafe Silicone Phone Holder Pink | F4: MagSafe Silicone Phone Grip - Pink | G4: Mounts & Holders | H4: Wallets, Card Holders & Grips | I4: MagSafe Silicone Phone Grip | J4: 108561483 | K4: Keep source SKU | L4: 2 | N4: =IF(M4<>"",M4,L4) -> 2 | O4: 29 | Q4: =IF(P4<>"",P4,O4) -> 29 | R4: Ready | S4: Rename from Phone Holder to Phone Grip; group all colours. | T4: A MagSafe pop socket/grip belongs with phone grips, not vehicle mounts. | U4: Not included in export; retrieve/verify in RepairDesk before import | V4: =IF(C4="Exclude","EXCLUDE",IF(OR(C4="Clarify",N4<=0,Q4<=0,R4="Verify cost and retail"),"REVIEW","READY")) -> READY | W4: Pending
A5: 6 | B5: 10855 | C5: Import | D5: Card Holder & Pop Scoket > Magsafe Pop Scoket | E5: Magsafe Silicone Phone Holder Sky Blue | F5: MagSafe Silicone Phone Grip - Sky Blue | G5: Mounts & Holders | H5: Wallets, Card Holders & Grips | I5: MagSafe Silicone Phone Grip | J5: 108551482 | K5: Keep source SKU | L5: 2 | N5: =IF(M5<>"",M5,L5) -> 2 | O5: 29 | Q5: =IF(P5<>"",P5,O5) -> 29 | R5: Ready | S5: Rename from Phone Holder to Phone Grip; group all colours. | T5: A MagSafe pop socket/grip belongs with phone grips, not vehicle mounts. | U5: Not included in export; retrieve/verify in RepairDesk before import | V5: =IF(C5="Exclude","EXCLUDE",IF(OR(C5="Clarify",N5<=0,Q5<=0,R5="Verify cost and retail"),"REVIEW","READY")) -> READY | W5: Pending
A6: 7 | B6: 10854 | C6: Import | D6: Card Holder & Pop Scoket > Magsafe Pop Scoket | E6: Magsafe Silicone Phone Holder Black | F6: MagSafe Silicone Phone Grip - Black | G6: Mounts & Holders | H6: Wallets, Card Holders & Grips | I6: MagSafe Silicone Phone Grip | J6: 108541481 | K6: Keep source SKU | L6: 2 | N6: =IF(M6<>"",M6,L6) -> 2 | O6: 29 | Q6: =IF(P6<>"",P6,O6) -> 29 | R6: Ready | S6: Rename from Phone Holder to Phone Grip; group all colours. | T6: A MagSafe pop socket/grip belongs with phone grips, not vehicle mounts. | U6: Not included in export; retrieve/verify in RepairDesk before import | V6: =IF(C6="Exclude","EXCLUDE",IF(OR(C6="Clarify",N6<=0,Q6<=0,R6="Verify cost and retail"),"REVIEW","READY")) -> READY | W6: Pending
A7: 8 | B7: 10853 | C7: Import | D7: Card Holder & Pop Scoket > Magsafe Card Holder | E7: Magsafe Card Holder Muti-Wallet Brown | F7: MagSafe Multi-Wallet - Brown | G7: Mounts & Holders | H7: Wallets, Card Holders & Grips | I7: MagSafe Multi-Wallet | J7: 108531480 | K7: Keep source SKU | L7: 3 | N7: =IF(M7<>"",M7,L7) -> 3 | O7: 35 | Q7: =IF(P7<>"",P7,O7) -> 35 | R7: Ready | S7: Correct Muti-Wallet to Multi-Wallet; group all colours. | T7: This is a phone wallet accessory. | U7: Not included in export; retrieve/verify in RepairDesk before import | V7: =IF(C7="Exclude","EXCLUDE",IF(OR(C7="Clarify",N7<=0,Q7<=0,R7="Verify cost and retail"),"REVIEW","READY")) -> READY | W7: Pending
A8: 9 | B8: 10852 | C8: Import | D8: Card Holder & Pop Scoket > Magsafe Card Holder | E8: Magsafe Card Holder Muti-Wallet Black | F8: MagSafe Multi-Wallet - Black | G8: Mounts & Holders | H8: Wallets, Card Holders & Grips | I8: MagSafe Multi-Wallet | J8: 108521479 | K8: Keep source SKU | L8: 3 | N8: =IF(M8<>"",M8,L8) -> 3 | O8: 35 | Q8: =IF(P8<>"",P8,O8) -> 35 | R8: Ready | S8: Correct Muti-Wallet to Multi-Wallet; group all colours. | T8: This is a phone wallet accessory. | U8: Not included in export; retrieve/verify in RepairDesk before import | V8: =IF(C8="Exclude","EXCLUDE",IF(OR(C8="Clarify",N8<=0,Q8<=0,R8="Verify cost and retail"),"REVIEW","READY")) -> READY | W8: Pending
A9: 10 | B9: 10851 | C9: Import | D9: Card Holder & Pop Scoket > Magsafe Card Holder | E9: Magsafe Card Holder Muti-Wallet Gray | F9: MagSafe Multi-Wallet - Grey | G9: Mounts & Holders | H9: Wallets, Card Holders & Grips | I9: MagSafe Multi-Wallet | J9: 108511478 | K9: Keep source SKU | L9: 3 | N9: =IF(M9<>"",M9,L9) -> 3 | O9: 35 | Q9: =IF(P9<>"",P9,O9) -> 35 | R9: Ready | S9: Correct Muti-Wallet to Multi-Wallet and Gray to Grey; group all colours. | T9: This is a phone wallet accessory. | U9: Not included in export; retrieve/verify in RepairDesk before import | V9: =IF(C9="Exclude","EXCLUDE",IF(OR(C9="Clarify",N9<=0,Q9<=0,R9="Verify cost and retail"),"REVIEW","READY")) -> READY | W9: Pending
A10: 11 | B10: 10322 | C10: Import | D10: Card Holder & Pop Scoket | E10: CTF EARBUDS POUCH | F10: CTF Earbuds Pouch | G10: Other Electronics | H10: Earbud Cases | I10: CTF Earbuds Pouch | J10: 1032168 | K10: Create new SKU; source SKU is duplicated | L10: 0 | M10: 5 | N10: =IF(M10<>"",M10,L10) -> 5 | O10: 32.99 | Q10: =IF(P10<>"",P10,O10) -> 32.99 | R10: Missing cost | S10: Enter cost and replace duplicated SKU 1032168. | T10: A protective pouch for earbuds belongs with earbud cases. | U10: Not included in export; retrieve/verify in RepairDesk before import | V10: =IF(C10="Exclude","EXCLUDE",IF(OR(C10="Clarify",N10<=0,Q10<=0,R10="Verify cost and retail"),"REVIEW","READY")) -> READY | W10: Pending
A11: 12 | B11: 10321 | C11: Clarify | D11: Card Holder & Pop Scoket | E11: CTF CARHOLDER & GRIP MAGSAFE STAND | F11: CTF MagSafe Car Holder / Phone Grip Stand | I11: CTF MagSafe Stand | J11: 1032168 | K11: Create new SKU; source SKU is duplicated | L11: 10 | N11: =IF(M11<>"",M11,L11) -> 10 | O11: 32.99 | Q11: =IF(P11<>"",P11,O11) -> 32.99 | R11: Ready | S11: Confirm from the image whether this is a vehicle mount or a phone grip/stand, then select the category; replace duplicated SKU 1032168. | T11: The current name describes both a car holder and a grip, which map to different POS categories. | U11: Not included in export; retrieve/verify in RepairDesk before import | V11: =IF(C11="Exclude","EXCLUDE",IF(OR(C11="Clarify",N11<=0,Q11<=0,R11="Verify cost and retail"),"REVIEW","READY")) -> REVIEW | W11: Pending
A12: 13 | B12: 8974 | C12: Clarify | D12: Uncategorized | E12: Card Strap Holder | F12: Card Strap Holder | G12: Mounts & Holders | H12: Wallets, Card Holders & Grips | I12: Phone Strap Accessories | J12: 8974626 | K12: Keep source SKU | L12: 0 | M12: 1 | N12: =IF(M12<>"",M12,L12) -> 1 | O12: 15 | Q12: =IF(P12<>"",P12,O12) -> 15 | R12: Missing cost | S12: Confirm product image and exact name, then enter cost. | T12: Likely a phone strap insert/card, but the current name is not specific enough. | U12: Not included in export; retrieve/verify in RepairDesk before import | V12: =IF(C12="Exclude","EXCLUDE",IF(OR(C12="Clarify",N12<=0,Q12<=0,R12="Verify cost and retail"),"REVIEW","READY")) -> REVIEW | W12: Pending
A13: 14 | B13: 8633 | C13: Exclude | D13: Uncategorized | E13: Techm8 Small Bag | F13: TechM8 Small Bag | J13: 8633797 | K13: Keep internal reference only | L13: 0 | M13: 1 | N13: =IF(M13<>"",M13,L13) -> 1 | O13: 0 | Q13: =IF(P13<>"",P13,O13) -> 0 | R13: Not applicable | S13: Keep as internal packaging/consumable, not a sellable POS product. | T13: A zero-price store bag is packaging rather than catalogue merchandise. | U13: Not required | V13: =IF(C13="Exclude","EXCLUDE",IF(OR(C13="Clarify",N13<=0,Q13<=0,R13="Verify cost and retail"),"REVIEW","READY")) -> EXCLUDE | W13: Pending
A14: 15 | B14: 8632 | C14: Exclude | D14: Uncategorized | E14: Techm8 Big Bag | F14: TechM8 Big Bag | J14: 8632796 | K14: Keep internal reference only | L14: 0 | M14: 1 | N14: =IF(M14<>"",M14,L14) -> 1 | O14: 0 | Q14: =IF(P14<>"",P14,O14) -> 0 | R14: Not applicable | S14: Keep as internal packaging/consumable, not a sellable POS product. | T14: A zero-price store bag is packaging rather than catalogue merchandise. | U14: Not required | V14: =IF(C14="Exclude","EXCLUDE",IF(OR(C14="Clarify",N14<=0,Q14<=0,R14="Verify cost and retail"),"REVIEW","READY")) -> EXCLUDE | W14: Pending
A15: 16 | B15: 8483 | C15: Clarify | D15: Drone | E15: Drone Map | F15: Drone Landing Mat (confirm) | G15: Other Electronics | H15: Drones & Accessories | I15: Drone Accessories | J15: 8483784 | K15: Keep source SKU | L15: 0 | M15: 5 | N15: =IF(M15<>"",M15,L15) -> 5 | O15: 25 | Q15: =IF(P15<>"",P15,O15) -> 25 | R15: Missing cost | S15: Confirm whether Drone Map is a typo for Drone Mat/Landing Pad; provide image and cost. | T15: The source name does not identify the physical product reliably. | U15: Not included in export; retrieve/verify in RepairDesk before import | V15: =IF(C15="Exclude","EXCLUDE",IF(OR(C15="Clarify",N15<=0,Q15<=0,R15="Verify cost and retail"),"REVIEW","READY")) -> REVIEW | W15: Pending
A16: 17 | B16: 8416 | C16: Exclude | D16: Uncategorized | E16: Special Order | F16: Special Order | J16: 8416553 | K16: Do not create product SKU | L16: 0 | N16: =IF(M16<>"",M16,L16) -> 0 | O16: 0 | Q16: =IF(P16<>"",P16,O16) -> 0 | R16: Not applicable | S16: Use the existing Special Products workflow instead of a permanent product. | T16: This is a transaction placeholder, not merchandise. | U16: Not required | V16: =IF(C16="Exclude","EXCLUDE",IF(OR(C16="Clarify",N16<=0,Q16<=0,R16="Verify cost and retail"),"REVIEW","READY")) -> EXCLUDE | W16: Pending
A17: 18 | B17: 8412 | C17: Import | D17: Uncategorized | E17: Phone Strap Gasket | F17: Phone Strap Adapter Patch | G17: Mounts & Holders | H17: Wallets, Card Holders & Grips | I17: Phone Strap Accessories | J17: 8412763 | K17: Keep source SKU | L17: 0 | M17: 0.5 | N17: =IF(M17<>"",M17,L17) -> 0.5 | O17: 1 | Q17: =IF(P17<>"",P17,O17) -> 1 | R17: Missing cost | S17: Rename Gasket to Adapter Patch and enter cost; confirm whether $1 retail remains correct. | T17: This is the insert used to attach a strap to a phone case. | U17: Not included in export; retrieve/verify in RepairDesk before import | V17: =IF(C17="Exclude","EXCLUDE",IF(OR(C17="Clarify",N17<=0,Q17<=0,R17="Verify cost and retail"),"REVIEW","READY")) -> READY | W17: Pending
A18: 19 | B18: 8411 | C18: Import | D18: Uncategorized | E18: Phone Strap | F18: Phone Lanyard Strap | G18: Mounts & Holders | H18: Wallets, Card Holders & Grips | I18: Phone Strap Accessories | J18: 8411762 | K18: Keep source SKU | L18: 0 | M18: 3 | N18: =IF(M18<>"",M18,L18) -> 3 | O18: 15 | Q18: =IF(P18<>"",P18,O18) -> 15 | R18: Missing cost | S18: Use a customer-readable name and enter cost. | T18: A phone carry strap is grouped with grips and card holders. | U18: Not included in export; retrieve/verify in RepairDesk before import | V18: =IF(C18="Exclude","EXCLUDE",IF(OR(C18="Clarify",N18<=0,Q18<=0,R18="Verify cost and retail"),"REVIEW","READY")) -> READY | W18: Pending
A19: 20 | B19: 8263 | C19: Import | D19: Drone | E19: FIMI X8 MINI V2 | F19: FIMI X8 Mini V2 Drone | G19: Other Electronics | H19: Drones & Accessories | I19: FIMI X8 Mini V2 Drone | J19: 8263681 | K19: Keep source SKU | L19: 0 | M19: 550 | N19: =IF(M19<>"",M19,L19) -> 550 | O19: 599 | Q19: =IF(P19<>"",P19,O19) -> 599 | R19: Missing cost | S19: Add Drone to the name and enter the purchase cost before import. | T19: The product itself is a drone. | U19: Not included in export; retrieve/verify in RepairDesk before import | V19: =IF(C19="Exclude","EXCLUDE",IF(OR(C19="Clarify",N19<=0,Q19<=0,R19="Verify cost and retail"),"REVIEW","READY")) -> READY | W19: Pending
A20: 21 | B20: 8041 | C20: Import | D20: Card Holder & Pop Scoket > Magsafe Card Holder | E20: Magsafe Card Holder Navy | F20: MagSafe Card Wallet - Navy | G20: Mounts & Holders | H20: Wallets, Card Holders & Grips | I20: MagSafe Card Wallet | J20: 8041585 | K20: Keep source SKU | L20: 0 | M20: 10 | N20: =IF(M20<>"",M20,L20) -> 10 | O20: 39.95 | Q20: =IF(P20<>"",P20,O20) -> 39.95 | R20: Missing cost | S20: Standardize name, enter cost and group all colours. | T20: This is a phone wallet/card holder. | U20: Not included in export; retrieve/verify in RepairDesk before import | V20: =IF(C20="Exclude","EXCLUDE",IF(OR(C20="Clarify",N20<=0,Q20<=0,R20="Verify cost and retail"),"REVIEW","READY")) -> READY | W20: Pending
A21: 22 | B21: 8040 | C21: Import | D21: Card Holder & Pop Scoket > Magsafe Card Holder | E21: Magsafe Card Holder Orange | F21: MagSafe Card Wallet - Orange | G21: Mounts & Holders | H21: Wallets, Card Holders & Grips | I21: MagSafe Card Wallet | J21: 8040584 | K21: Keep source SKU | L21: 0 | M21: 10 | N21: =IF(M21<>"",M21,L21) -> 10 | O21: 39.95 | Q21: =IF(P21<>"",P21,O21) -> 39.95 | R21: Missing cost | S21: Standardize name, enter cost and group all colours. | T21: This is a phone wallet/card holder. | U21: Not included in export; retrieve/verify in RepairDesk before import | V21: =IF(C21="Exclude","EXCLUDE",IF(OR(C21="Clarify",N21<=0,Q21<=0,R21="Verify cost and retail"),"REVIEW","READY")) -> READY | W21: Pending
A22: 23 | B22: 8039 | C22: Import | D22: Card Holder & Pop Scoket > Magsafe Card Holder | E22: Magsafe Card Holder Red | F22: MagSafe Card Wallet - Red | G22: Mounts & Holders | H22: Wallets, Card Holders & Grips | I22: MagSafe Card Wallet | J22: 8039583 | K22: Keep source SKU | L22: 0 | M22: 10 | N22: =IF(M22<>"",M22,L22) -> 10 | O22: 39.95 | Q22: =IF(P22<>"",P22,O22) -> 39.95 | R22: Missing cost | S22: Standardize name, enter cost and group all colours. | T22: This is a phone wallet/card holder. | U22: Not included in export; retrieve/verify in RepairDesk before import | V22: =IF(C22="Exclude","EXCLUDE",IF(OR(C22="Clarify",N22<=0,Q22<=0,R22="Verify cost and retail"),"REVIEW","READY")) -> READY | W22: Pending
A23: 24 | B23: 8038 | C23: Import | D23: Card Holder & Pop Scoket > Magsafe Card Holder | E23: Magsafe Card Holder Green | F23: MagSafe Card Wallet - Green | G23: Mounts & Holders | H23: Wallets, Card Holders & Grips | I23: MagSafe Card Wallet | J23: 8038582 | K23: Keep source SKU | L23: 0 | M23: 10 | N23: =IF(M23<>"",M23,L23) -> 10 | O23: 39.95 | Q23: =IF(P23<>"",P23,O23) -> 39.95 | R23: Missing cost | S23: Standardize name, enter cost and group all colours. | T23: This is a phone wallet/card holder. | U23: Not included in export; retrieve/verify in RepairDesk before import | V23: =IF(C23="Exclude","EXCLUDE",IF(OR(C23="Clarify",N23<=0,Q23<=0,R23="Verify cost and retail"),"REVIEW","READY")) -> READY | W23: Pending
A24: 25 | B24: 8036 | C24: Import | D24: Card Holder & Pop Scoket > Magsafe Card Holder | E24: Magsafe Card Holder Brown | F24: MagSafe Card Wallet - Brown | G24: Mounts & Holders | H24: Wallets, Card Holders & Grips | I24: MagSafe Card Wallet | J24: 8036580 | K24: Keep source SKU | L24: 0 | M24: 10 | N24: =IF(M24<>"",M24,L24) -> 10 | O24: 39.95 | Q24: =IF(P24<>"",P24,O24) -> 39.95 | R24: Missing cost | S24: Standardize name, enter cost and group all colours. | T24: This is a phone wallet/card holder. | U24: Not included in export; retrieve/verify in RepairDesk before import | V24: =IF(C24="Exclude","EXCLUDE",IF(OR(C24="Clarify",N24<=0,Q24<=0,R24="Verify cost and retail"),"REVIEW","READY")) -> READY | W24: Pending
A25: 26 | B25: 7763 | C25: Clarify | D25: Uncategorized | E25: Phone tag | F25: Phone Tag (exact product required) | G25: Other Electronics | H25: Other Electronics | I25: Phone Tag | J25: 776330 | K25: Keep source SKU | L25: 0 | M25: 2 | N25: =IF(M25<>"",M25,L25) -> 2 | O25: 5 | Q25: =IF(P25<>"",P25,O25) -> 5 | R25: Missing cost | S25: Provide the product image/function and cost; current name is too broad to classify confidently. | T25: Phone Tag could mean an NFC tag, label, tracker accessory or another item. | U25: Not included in export; retrieve/verify in RepairDesk before import | V25: =IF(C25="Exclude","EXCLUDE",IF(OR(C25="Clarify",N25<=0,Q25<=0,R25="Verify cost and retail"),"REVIEW","READY")) -> REVIEW | W25: Pending
A26: 27 | B26: 7148 | C26: Import | D26: Card Holder & Pop Scoket > Sticker Card Holder | E26: Silicone Card Holder Black | F26: Adhesive Silicone Card Holder - Black | G26: Mounts & Holders | H26: Wallets, Card Holders & Grips | I26: Adhesive Silicone Card Holder | J26: 7148331 | K26: Keep source SKU | L26: 0 | M26: 2 | N26: =IF(M26<>"",M26,L26) -> 2 | O26: 10 | Q26: =IF(P26<>"",P26,O26) -> 10 | R26: Missing cost | S26: Add Adhesive to distinguish it from MagSafe wallets; enter cost and group colours. | T26: A stick-on phone card holder belongs with phone wallets and grips. | U26: Not included in export; retrieve/verify in RepairDesk before import | V26: =IF(C26="Exclude","EXCLUDE",IF(OR(C26="Clarify",N26<=0,Q26<=0,R26="Verify cost and retail"),"REVIEW","READY")) -> READY | W26: Pending
A27: 28 | B27: 7147 | C27: Import | D27: Card Holder & Pop Scoket > Sticker Card Holder | E27: Silicone Card Holder Green | F27: Adhesive Silicone Card Holder - Green | G27: Mounts & Holders | H27: Wallets, Card Holders & Grips | I27: Adhesive Silicone Card Holder | J27: 7147330 | K27: Keep source SKU | L27: 0 | M27: 2 | N27: =IF(M27<>"",M27,L27) -> 2 | O27: 10 | Q27: =IF(P27<>"",P27,O27) -> 10 | R27: Missing cost | S27: Add Adhesive to distinguish it from MagSafe wallets; enter cost and group colours. | T27: A stick-on phone card holder belongs with phone wallets and grips. | U27: Not included in export; retrieve/verify in RepairDesk before import | V27: =IF(C27="Exclude","EXCLUDE",IF(OR(C27="Clarify",N27<=0,Q27<=0,R27="Verify cost and retail"),"REVIEW","READY")) -> READY | W27: Pending
A28: 29 | B28: 7146 | C28: Import | D28: Card Holder & Pop Scoket > Sticker Card Holder | E28: Silicone Card Holder Yellow | F28: Adhesive Silicone Card Holder - Yellow | G28: Mounts & Holders | H28: Wallets, Card Holders & Grips | I28: Adhesive Silicone Card Holder | J28: 7146329 | K28: Keep source SKU | L28: 0 | M28: 2 | N28: =IF(M28<>"",M28,L28) -> 2 | O28: 10 | Q28: =IF(P28<>"",P28,O28) -> 10 | R28: Missing cost | S28: Add Adhesive to distinguish it from MagSafe wallets; enter cost and group colours. | T28: A stick-on phone card holder belongs with phone wallets and grips. | U28: Not included in export; retrieve/verify in RepairDesk before import | V28: =IF(C28="Exclude","EXCLUDE",IF(OR(C28="Clarify",N28<=0,Q28<=0,R28="Verify cost and retail"),"REVIEW","READY")) -> READY | W28: Pending
A29: 30 | B29: 6769 | C29: Exclude | D29: Uncategorized | E29: Shop Credit | F29: Shop Credit | J29: 676992 | K29: Do not create product SKU | L29: 0 | N29: =IF(M29<>"",M29,L29) -> 0 | O29: 0 | Q29: =IF(P29<>"",P29,O29) -> 0 | R29: Not applicable | S29: Handle as store credit/payment logic, not as inventory merchandise. | T29: Shop credit is a financial balance, not a physical product. | U29: Not required | V29: =IF(C29="Exclude","EXCLUDE",IF(OR(C29="Clarify",N29<=0,Q29<=0,R29="Verify cost and retail"),"REVIEW","READY")) -> EXCLUDE | W29: Pending
A30: 31 | B30: 6062 | C30: Import | D30: Uncategorized | E30: RGB Digital Clock | F30: RGB Digital Clock | G30: Other Electronics | H30: Lighting & Clocks | I30: RGB Digital Clock | J30: 606257 | K30: Keep source SKU | L30: 179 | M30: 100 | N30: =IF(M30<>"",M30,L30) -> 100 | O30: 179 | Q30: =IF(P30<>"",P30,O30) -> 179 | R30: Verify cost and retail | S30: Cost and retail are both $179. Confirm the true cost and whether $179 is the correct sale price. | T30: A digital RGB clock belongs with lighting and clocks. | U30: Not included in export; retrieve/verify in RepairDesk before import | V30: =IF(C30="Exclude","EXCLUDE",IF(OR(C30="Clarify",N30<=0,Q30<=0,R30="Verify cost and retail"),"REVIEW","READY")) -> REVIEW | W30: Pending
A31: 32 | B31: 6061 | C31: Import | D31: Uncategorized | E31: Music Reactive RGB Light | F31: Music-Reactive RGB Light | G31: Other Electronics | H31: Lighting & Clocks | I31: Music-Reactive RGB Light | J31: 606156 | K31: Keep source SKU | L31: 79 | M31: 40 | N31: =IF(M31<>"",M31,L31) -> 40 | O31: 79 | Q31: =IF(P31<>"",P31,O31) -> 79 | R31: Verify cost and retail | S31: Cost and retail are both $79. Confirm the true cost and whether $79 is the correct sale price. | T31: This is decorative lighting. | U31: Not included in export; retrieve/verify in RepairDesk before import | V31: =IF(C31="Exclude","EXCLUDE",IF(OR(C31="Clarify",N31<=0,Q31<=0,R31="Verify cost and retail"),"REVIEW","READY")) -> REVIEW | W31: Pending
A32: 33 | B32: 6021 | C32: Exclude | D32: Uncategorized | E32: Special | F32: Special | J32: 595728 | K32: Duplicate SKU is irrelevant because product is excluded | L32: 5 | M32: 1 | N32: =IF(M32<>"",M32,L32) -> 1 | O32: 5 | Q32: =IF(P32<>"",P32,O32) -> 5 | R32: Not applicable | S32: Use Special Products; do not migrate this placeholder. | T32: This is a generic transaction placeholder. | U32: Not required | V32: =IF(C32="Exclude","EXCLUDE",IF(OR(C32="Clarify",N32<=0,Q32<=0,R32="Verify cost and retail"),"REVIEW","READY")) -> EXCLUDE | W32: Pending
A33: 34 | B33: 5995 | C33: Import | D33: Uncategorized | E33: Stylus Paragon Pen | F33: Paragon Stylus Pen | G33: Other Electronics | H33: Other Electronics | I33: Paragon Stylus Pen | J33: 597334 | K33: Keep source SKU | L33: 0 | M33: 2 | N33: =IF(M33<>"",M33,L33) -> 2 | O33: 10 | Q33: =IF(P33<>"",P33,O33) -> 10 | R33: Missing cost | S33: Standardize word order and enter cost. | T33: A general tablet/phone stylus has no more specific current POS category. | U33: Not included in export; retrieve/verify in RepairDesk before import | V33: =IF(C33="Exclude","EXCLUDE",IF(OR(C33="Clarify",N33<=0,Q33<=0,R33="Verify cost and retail"),"REVIEW","READY")) -> READY | W33: Pending
A34: 35 | B34: 5957 | C34: Exclude | D34: Uncategorized | E34: MIS & Other Products | F34: Miscellaneous & Other Products | J34: 595728 | K34: Duplicate SKU is irrelevant because product is excluded | L34: 0 | N34: =IF(M34<>"",M34,L34) -> 0 | O34: 0 | Q34: =IF(P34<>"",P34,O34) -> 0 | R34: Not applicable | S34: Use Special Products; do not migrate this generic placeholder. | T34: This is a generic transaction placeholder. | U34: Not required | V34: =IF(C34="Exclude","EXCLUDE",IF(OR(C34="Clarify",N34<=0,Q34<=0,R34="Verify cost and retail"),"REVIEW","READY")) -> EXCLUDE | W34: Pending
A35: 36 | B35: 5934 | C35: Clarify | D35: Uncategorized | E35: $2 SIM | F35: $2 SIM Starter Pack (carrier required) | G35: Other Electronics | H35: Other Electronics | I35: SIM Starter Pack | J35: 593419 | K35: Keep source SKU | L35: 0 | N35: =IF(M35<>"",M35,L35) -> 0 | O35: 2 | Q35: =IF(P35<>"",P35,O35) -> 2 | R35: Missing cost | S35: Confirm carrier, exact product name, image and whether zero cost is genuine. | T35: A carrier SIM can be a sellable product, but the current name is incomplete. | U35: Not included in export; retrieve/verify in RepairDesk before import | V35: =IF(C35="Exclude","EXCLUDE",IF(OR(C35="Clarify",N35<=0,Q35<=0,R35="Verify cost and retail"),"REVIEW","READY")) -> REVIEW | W35: Pending
